smartbonus/__init__.py
smartbonus/app.py
smartbonus/models.py
smartbonus/utils.py
tests/__init__.py
tests/smartbonus.py
smartbonuspy-0.0.6.dist-info/LICENSE
smartbonuspy-0.0.6.dist-info/METADATA
smartbonuspy-0.0.6.dist-info/WHEEL
smartbonuspy-0.0.6.dist-info/top_level.txt
smartbonuspy-0.0.6.dist-info/RECORD
