Metadata-Version: 2.1
Name: smartbonuspy
Version: 0.0.6
Summary: This package provides Python implementation of Smartbonus api. Supported all public api of smartbonus.
Home-page: https://github.com/srostyslav/smartbonuspy
Author: Rostyslav
Author-email: rostyslav.rigroup@gmail.com
License: UNKNOWN
Platform: UNKNOWN
Classifier: Programming Language :: Python :: 3
Classifier: License :: OSI Approved :: MIT License
Classifier: Operating System :: OS Independent
Requires-Python: >=3.6
License-File: LICENSE
